miyabi/__init__.py
miyabi/core.py
miyabi/utils.py
miyabi256-0.1.2.dist-info/licenses/LICENSE
miyabi256-0.1.2.dist-info/METADATA
miyabi256-0.1.2.dist-info/WHEEL
miyabi256-0.1.2.dist-info/top_level.txt
miyabi256-0.1.2.dist-info/RECORD
