Metadata-Version: 2.4
Name: miyabi256
Version: 0.1.2
Summary: A Base64-like encoder/decoder using 256 Japanese characters (Hiragana, Katakana, Kanji).
Home-page: https://github.com/eightman999/Miyabi256
Author: eightman
Author-email: eightman124@gmail.com
Classifier: Programming Language :: Python :: 3
Classifier: License :: OSI Approved :: MIT License
Classifier: Operating System :: OS Independent
Classifier: Topic :: Text Processing
Classifier: Topic :: Utilities
Requires-Python: >=3.6
License-File: LICENSE
Dynamic: author
Dynamic: author-email
Dynamic: classifier
Dynamic: description
Dynamic: description-content-type
Dynamic: home-page
Dynamic: license-file
Dynamic: requires-python
Dynamic: summary
